apismartkit/__init__.py
apismartkit/client.py
apismartkit/config.py
apismartkit/endpoint.py
apismartkit/enums.py
apismartkit/exceptions.py
apismartkit/interfaces.py
apismartkit/middlewares.py
apismartkit/pagination.py
apismartkit/request.py
apismartkit/response.py
apismartkit/schemas.py
apismartkit-0.0.1.dist-info/METADATA
apismartkit-0.0.1.dist-info/WHEEL
apismartkit-0.0.1.dist-info/RECORD
