Metadata-Version: 2.4
Name: apismartkit
Version: 0.0.1
Summary: Умный и мощный Python клиент для работы с REST API с синхронным и асинхронным интерфейсом, встроенной валидацией, пагинацией, повторными попытками и middleware системой
License: MIT
Keywords: api-client,rest-api,http-client,async,pydantic,validation,pagination,retry,middleware,circuit-breaker
Author: skulap
Author-email: skulap01@gmail.com
Requires-Python: >=3.12,<4.0
Classifier: License :: OSI Approved :: MIT License
Classifier: Programming Language :: Python :: 3
Classifier: Programming Language :: Python :: 3.12
Classifier: Programming Language :: Python :: 3.13
Classifier: Programming Language :: Python :: 3.14
Requires-Dist: httpx (>=0.28.1,<0.29.0)
Requires-Dist: pydantic (>=2.11.10,<3.0.0)
Requires-Dist: tenacity (>=9.1.2,<10.0.0)
